keystoneclient/__init__.py
keystoneclient/_discover.py
keystoneclient/access.py
keystoneclient/adapter.py
keystoneclient/base.py
keystoneclient/baseclient.py
keystoneclient/client.py
keystoneclient/discover.py
keystoneclient/exceptions.py
keystoneclient/httpclient.py
keystoneclient/i18n.py
keystoneclient/service_catalog.py
keystoneclient/session.py
keystoneclient/utils.py
keystoneclient/auth/__init__.py
keystoneclient/auth/base.py
keystoneclient/auth/cli.py
keystoneclient/auth/conf.py
keystoneclient/auth/token_endpoint.py
keystoneclient/auth/identity/__init__.py
keystoneclient/auth/identity/access.py
keystoneclient/auth/identity/base.py
keystoneclient/auth/identity/v2.py
keystoneclient/auth/identity/generic/__init__.py
keystoneclient/auth/identity/generic/base.py
keystoneclient/auth/identity/generic/cli.py
keystoneclient/auth/identity/generic/password.py
keystoneclient/auth/identity/generic/token.py
keystoneclient/auth/identity/v3/__init__.py
keystoneclient/auth/identity/v3/base.py
keystoneclient/auth/identity/v3/federated.py
keystoneclient/auth/identity/v3/password.py
keystoneclient/auth/identity/v3/token.py
keystoneclient/common/__init__.py
keystoneclient/common/cms.py
keystoneclient/contrib/__init__.py
keystoneclient/contrib/auth/__init__.py
keystoneclient/contrib/auth/v3/__init__.py
keystoneclient/contrib/auth/v3/oidc.py
keystoneclient/contrib/auth/v3/saml2.py
keystoneclient/contrib/ec2/__init__.py
keystoneclient/contrib/ec2/utils.py
keystoneclient/fixture/__init__.py
keystoneclient/fixture/discovery.py
keystoneclient/fixture/exception.py
keystoneclient/fixture/v2.py
keystoneclient/fixture/v3.py
keystoneclient/generic/__init__.py
keystoneclient/generic/client.py
keystoneclient/tests/__init__.py
keystoneclient/tests/functional/__init__.py
keystoneclient/tests/functional/base.py
keystoneclient/tests/functional/test_base.py
keystoneclient/tests/functional/v3/__init__.py
keystoneclient/tests/functional/v3/client_fixtures.py
python_keystoneclient-5.7.0.dist-info/AUTHORS
python_keystoneclient-5.7.0.dist-info/LICENSE
python_keystoneclient-5.7.0.dist-info/METADATA
python_keystoneclient-5.7.0.dist-info/WHEEL
python_keystoneclient-5.7.0.dist-info/entry_points.txt
python_keystoneclient-5.7.0.dist-info/pbr.json
python_keystoneclient-5.7.0.dist-info/top_level.txt
python_keystoneclient-5.7.0.dist-info/RECORD
