Metadata-Version: 2.1
Name: python-keystoneclient
Version: 5.7.0
Summary: Client Library for OpenStack Identity
Home-page: https://docs.openstack.org/python-keystoneclient/latest/
Author: OpenStack
Author-email: openstack-discuss@lists.openstack.org
Classifier: Environment :: OpenStack
Classifier: Intended Audience :: Information Technology
Classifier: Intended Audience :: System Administrators
Classifier: License :: OSI Approved :: Apache Software License
Classifier: Operating System :: POSIX :: Linux
Classifier: Programming Language :: Python
Classifier: Programming Language :: Python :: 3
Classifier: Programming Language :: Python :: 3.10
Classifier: Programming Language :: Python :: 3.11
Classifier: Programming Language :: Python :: 3.12
Requires-Python: >=3.10
License-File: LICENSE
Requires-Dist: pbr>=2.0.0
Requires-Dist: debtcollector>=1.2.0
Requires-Dist: keystoneauth1>=3.4.0
Requires-Dist: oslo.config>=5.2.0
Requires-Dist: oslo.i18n>=3.15.3
Requires-Dist: oslo.serialization>=2.18.0
Requires-Dist: oslo.utils>=3.33.0
Requires-Dist: requests>=2.14.2
Requires-Dist: stevedore>=1.20.0
Requires-Dist: packaging>=20.4
